{"cameraMode":{"drawMode":0,"name":"Shaded","section":"Shading Mode"},"sceneLighting":true,"audioPlay":false,"sceneViewState":{"showFog":true,"showMaterialUpdate":false,"showSkybox":true,"showFlares":true,"showImageEffects":true,"showParticleSystems":true},"in2DMode":false,"pivot":{"x":-191.14816284179688,"y":119.31749725341797,"z":-611.7413940429688},"rotation":{"x":0.06944210082292557,"y":0.2881597876548767,"z":-0.020960018038749696,"w":0.9548370242118836},"size":409.0661926269531,"orthographic":false}